riskfolio_beta/__init__.py
riskfolio_beta/core.py
riskfolio_beta/exceptions.py
riskfolio_beta/policies.py
riskfolio_beta/reporting.py
riskfolio_beta/scenario.py
riskfolio_beta/typing.py
riskfolio_beta/validators.py
riskfolio_beta-0.1.22.dist-info/METADATA
riskfolio_beta-0.1.22.dist-info/WHEEL
riskfolio_beta-0.1.22.dist-info/top_level.txt
riskfolio_beta-0.1.22.dist-info/RECORD
