Metadata-Version: 2.4
Name: riskfolio_beta
Version: 0.1.22
Summary: Risk-weighted assets attribution and capital optimization toolkit.
Home-page: https://github.com/yourname/finattrib
Author: Kerwin Liao
Author-email: Kerwin Liao <kerwin.p.lau@gmail.com>
License: MIT
Project-URL: Homepage, https://kerwinliao.github.io/
Project-URL: Source, https://github.com/kerwinliao/riskfolio
Classifier: Programming Language :: Python :: 3.11
Classifier: License :: OSI Approved :: MIT License
Classifier: Operating System :: OS Independent
Requires-Python: >=3.8
Requires-Dist: pandas>=1.5
Requires-Dist: numpy>=1.23
Requires-Dist: matplotlib>=3.5
Requires-Dist: scipy>=1.9
Dynamic: author
Dynamic: home-page
Dynamic: requires-python
